kerchunk/__init__.py
kerchunk/codecs.py
kerchunk/combine.py
kerchunk/df.py
kerchunk/fits.py
kerchunk/grib2.py
kerchunk/hdf.py
kerchunk/mzML.py
kerchunk/netCDF3.py
kerchunk/tiff.py
kerchunk/utils.py
kerchunk/xarray_backend.py
kerchunk/zarr.py
kerchunk/tests/air.nc
kerchunk/tests/air_linked.nc
kerchunk/tests/conftest.py
kerchunk/tests/gen_hdf5.py
kerchunk/tests/tinygrib.grb2
kerchunk-0.2.6.dist-info/LICENSE
kerchunk-0.2.6.dist-info/METADATA
kerchunk-0.2.6.dist-info/WHEEL
kerchunk-0.2.6.dist-info/entry_points.txt
kerchunk-0.2.6.dist-info/top_level.txt
kerchunk-0.2.6.dist-info/RECORD
