Metadata-Version: 2.1
Name: kerchunk
Version: 0.2.6
Summary: Functions to make reference descriptions for ReferenceFileSystem
Author-email: Martin Durant <martin.durant@alumni.utoronto.ca>
License: MIT
Project-URL: Documentation, https://fsspec.github.io/kerchunk
Project-URL: issue-tracker, https://github.com/fsspec/kerchunk/issues
Project-URL: source-code, https://github.com/fsspec/kerchunk
Classifier: License :: OSI Approved :: MIT License
Classifier: Operating System :: OS Independent
Classifier: Intended Audience :: Science/Research
Classifier: Programming Language :: Python
Classifier: Topic :: Scientific/Engineering
Classifier: Development Status :: 3 - Alpha
Classifier: Topic :: Scientific/Engineering
Requires-Python: >=3.7
License-File: LICENSE
Requires-Dist: fsspec
Requires-Dist: numcodecs
Requires-Dist: numpy
Requires-Dist: ujson
Requires-Dist: zarr
Provides-Extra: cftime
Requires-Dist: cftime; extra == "cftime"
Provides-Extra: fits
Requires-Dist: xarray; extra == "fits"
Provides-Extra: hdf
Requires-Dist: h5py; extra == "hdf"
Requires-Dist: xarray; extra == "hdf"
Provides-Extra: grib2
Requires-Dist: cfgrib; extra == "grib2"
Provides-Extra: netcdf3
Requires-Dist: scipy; extra == "netcdf3"
Provides-Extra: dev
Requires-Dist: cftime; extra == "dev"
Requires-Dist: dask; extra == "dev"
Requires-Dist: h5netcdf; extra == "dev"
Requires-Dist: h5py; extra == "dev"
Requires-Dist: jinja2; extra == "dev"
Requires-Dist: mypy; extra == "dev"
Requires-Dist: pytest; extra == "dev"
Requires-Dist: s3fs; extra == "dev"
Requires-Dist: types-ujson; extra == "dev"
Requires-Dist: xarray; extra == "dev"
Requires-Dist: xarray-datatree; extra == "dev"
Requires-Dist: cfgrib; extra == "dev"
Requires-Dist: scipy; extra == "dev"
Requires-Dist: netcdf4; extra == "dev"
